cdk8s_debore/__init__.py
cdk8s_debore/py.typed
cdk8s_debore/_jsii/__init__.py
cdk8s_debore/_jsii/cdk8s-debore@0.1.1.jsii.tgz
cdk8s_debore-0.1.1.dist-info/METADATA
cdk8s_debore-0.1.1.dist-info/WHEEL
cdk8s_debore-0.1.1.dist-info/top_level.txt
cdk8s_debore-0.1.1.dist-info/RECORD
