Metadata-Version: 2.1
Name: cdk8s-debore
Version: 0.1.1
Summary: Run your apps on Kubernetes cluster without bored YAMLing
Home-page: https://github.com/toricls/cdk8s-debore.git
Author: Tori<yshr@amazon.com>
License: Apache-2.0
Project-URL: Source, https://github.com/toricls/cdk8s-debore.git
Platform: UNKNOWN
Classifier: Intended Audience :: Developers
Classifier: Operating System :: OS Independent
Classifier: Programming Language :: JavaScript
Classifier: Programming Language :: Python :: 3 :: Only
Classifier: Programming Language :: Python :: 3.6
Classifier: Programming Language :: Python :: 3.7
Classifier: Programming Language :: Python :: 3.8
Classifier: Typing :: Typed
Classifier: Development Status :: 4 - Beta
Classifier: License :: OSI Approved
Requires-Python: >=3.6
Requires-Dist: jsii (<2.0.0,>=1.5.0)
Requires-Dist: publication (>=0.0.3)
Requires-Dist: cdk8s (<0.21.0,>=0.20.0)
Requires-Dist: constructs (<3.0.0,>=2.0.1)
